[
  {
    "title": "Cory Booker's 'Filibuster' Surpasses 21 Hours, Breaks Ted Cruz's Record",
    "score": 24857,
    "time": 1743541716.0
  },
  {
    "title": "20+HR",
    "score": 12190,
    "time": 1743546923.0
  },
  {
    "title": "This hotel has a very polite way of saying they will overcharge customers for items they may steal from their rooms.",
    "score": 9970,
    "time": 1743543122.0
  },
  {
    "title": "Morgan Wallen refused to do SNL sketch, was replaced by Joe Jonas",
    "score": 13507,
    "time": 1743533567.0
  },
  {
    "title": "For example",
    "score": 17096,
    "time": 1743531517.0
  },
  {
    "title": "What do you think of Senator Cory Booker's marathon speech (20 hours+ as of this post)?",
    "score": 10755,
    "time": 1743534930.0
  },
  {
    "title": "Millie Bobby Brown carries a pet microchip scanner to help stray dogs. She has saved over 230 dogs!",
    "score": 5809,
    "time": 1743544128.0
  },
  {
    "title": "Waltz and staff used Gmail for government communications, officials say",
    "score": 6617,
    "time": 1743541349.0
  },
  {
    "title": "Reason 69 why windows is shit",
    "score": 11448,
    "time": 1743534758.0
  },
  {
    "title": "\ud83d\udd25 This is Tanzania near the Roof of Africa (Mount Kilimanjaro).",
    "score": 11800,
    "time": 1743532387.0
  },
  {
    "title": "He keeps telling on himself",
    "score": 26323,
    "time": 1743524120.0
  },
  {
    "title": "United Healthcare takes the lives of paying clients without blinking they going on trial too?",
    "score": 38379,
    "time": 1743523221.0
  },
  {
    "title": "Eggs are finally cheap again here in Florida !! $1.49 !!!Thank you Trump !!!!",
    "score": 20421,
    "time": 1743528836.0
  },
  {
    "title": "U.S. Sen. Tammy Duckworth (D-IL) continues her attacks on Defense Secretary Pete Hegseth after calling him a \u201cfucking liar\u201d last week:\n\n\u201cLast week, I used some pretty colorful language to call Pete Hegseth a liar \u2026 I\u2019d like to call him a disgrace as well.\u201d",
    "score": 5536,
    "time": 1743542806.0
  },
  {
    "title": "Who does that judge work for? Karoline Leavitt's justification for ignoring a Federal judge's order",
    "score": 13390,
    "time": 1743528902.0
  },
  {
    "title": "Conmander n' Thief",
    "score": 10585,
    "time": 1743531208.0
  },
  {
    "title": "This girl saw a dolphin playing alone",
    "score": 7152,
    "time": 1743536936.0
  },
  {
    "title": "AIO if I left my bf for this",
    "score": 9457,
    "time": 1743535387.0
  },
  {
    "title": "And so it begins.........",
    "score": 18756,
    "time": 1743524511.0
  },
  {
    "title": "TIL In 2015, a Washington Post reporter wrote an article calling Red Lake County, Minnesota \"the absolute worst place to live in America\". He then visited the county and not only did he change his opinion. But 6 months later he and his family moved to Red Lake County.",
    "score": 6908,
    "time": 1743535999.0
  },
  {
    "title": "Cheers :)",
    "score": 17644,
    "time": 1743526816.0
  },
  {
    "title": "DOJ to seek death penalty for Luigi Mangione in CEO murder case",
    "score": 32149,
    "time": 1743520590.0
  },
  {
    "title": "Petah?",
    "score": 7050,
    "time": 1743535863.0
  },
  {
    "title": "who would hate the green guy",
    "score": 4989,
    "time": 1743540444.0
  },
  {
    "title": "THEY REALLY DON'T WANT US TO SHOW UP APR 5. HOLD THE LINE.",
    "score": 4396,
    "time": 1743541527.0
  }
]